Workbook

Sheet Sheet1
A1: columns | B1: 16384
A2: rows | B2: 1046576

Sheet Day 1
A1: SNO. | B1: NAME | C1: MATHS | D1: SCIENCE | E1: SST | F1: HINDI | G1: ENGLISH | H1: TOTAL MARKS | I1: PERCENTAGE | J1: FAIL/PASS STATUS | K1: COUNT | L1: COUNTBLANK | M1: COUNTA
A2: 1 | B2: AMAN | C2: 24 | D2: DYS | E2: 23 | F2: 8 | G2: 90 | H2: =SUM(C2:G2) -> 145 | I2: =H2/500 -> 0.29 | J2: =IF(I2>=33%,"PASS","FAIL") -> FAIL | K2: =COUNT(C2:G2) -> 4 | L2: =COUNTBLANK(C2:G2) -> 0 | M2: =COUNTA(C2:G2) -> 5
A3: 2 | B3: KARAN | C3: 68 | D3: 96 | F3: 27 | H3: =SUM(C3:G3) -> 191 | I3: =H3/500 -> 0.382 | J3: =IF(I3>=33%,"PASS","FAIL") -> PASS | K3: =COUNT(C3:G3) -> 3 | L3: =COUNTBLANK(C3:G3) -> 2 | M3: =COUNTA(C3:G3) -> 3
A4: 3 | B4: RAVI | C4: 91 | D4: 55 | E4: 71 | F4: 76 | G4: 46 | H4: =SUM(C4:G4) -> 339 | I4: =H4/500 -> 0.678 | J4: =IF(I4>=33%,"PASS","FAIL") -> PASS | K4: =COUNT(C4:G4) -> 5 | L4: =COUNTBLANK(C4:G4) -> 0 | M4: =COUNTA(C4:G4) -> 5
A5: 4 | B5: MOHAN | C5: 85 | D5: 58 | F5: 64 | G5: 27 | H5: =SUM(C5:G5) -> 234 | I5: =H5/500 -> 0.468 | J5: =IF(I5>=33%,"PASS","FAIL") -> PASS | K5: =COUNT(C5:G5) -> 4 | L5: =COUNTBLANK(C5:G5) -> 1 | M5: =COUNTA(C5:G5) -> 4
A6: 5 | B6: AKSHAY | C6: 100 | D6: 74 | E6: 76 | F6: 30 | G6: 74 | H6: =SUM(C6:G6) -> 354 | I6: =H6/500 -> 0.708 | J6: =IF(I6>=33%,"PASS","FAIL") -> PASS | K6: =COUNT(C6:G6) -> 5 | L6: =COUNTBLANK(C6:G6) -> 0 | M6: =COUNTA(C6:G6) -> 5
A7: 6 | B7: ATUL | C7: 30 | E7: 14 | F7: dfg | G7: 89 | H7: =SUM(C7:G7) -> 133 | I7: =H7/500 -> 0.266 | J7: =IF(I7>=33%,"PASS","FAIL") -> FAIL | K7: =COUNT(C7:G7) -> 3 | L7: =COUNTBLANK(C7:G7) -> 1 | M7: =COUNTA(C7:G7) -> 4
A8: 7 | B8: HARRY | C8: 66 | D8: 73 | E8: 93 | F8: 20 | G8: 30 | H8: =SUM(C8:G8) -> 282 | I8: =H8/500 -> 0.564 | J8: =IF(I8>=33%,"PASS","FAIL") -> PASS | K8: =COUNT(C8:G8) -> 5 | L8: =COUNTBLANK(C8:G8) -> 0 | M8: =COUNTA(C8:G8) -> 5
A9: 8 | B9: KOMAL | C9: 99 | D9: 42 | E9: 30 | F9: 95 | H9: =SUM(C9:G9) -> 266 | I9: =H9/500 -> 0.532 | J9: =IF(I9>=33%,"PASS","FAIL") -> PASS | K9: =COUNT(C9:G9) -> 4 | L9: =COUNTBLANK(C9:G9) -> 1 | M9: =COUNTA(C9:G9) -> 4
A10: 9 | B10: HARI | D10: 75 | E10: 6 | F10: 23 | G10: 56 | H10: =SUM(C10:G10) -> 160 | I10: =H10/500 -> 0.32 | J10: =IF(I10>=33%,"PASS","FAIL") -> FAIL | K10: =COUNT(C10:G10) -> 4 | L10: =COUNTBLANK(C10:G10) -> 1 | M10: =COUNTA(C10:G10) -> 4
A11: 10 | B11: HARSHITA | C11: 41 | D11: 94 | E11: 58 | F11: 9 | G11: 94 | H11: =SUM(C11:G11) -> 296 | I11: =H11/500 -> 0.592 | J11: =IF(I11>=33%,"PASS","FAIL") -> PASS | K11: =COUNT(C11:G11) -> 5 | L11: =COUNTBLANK(C11:G11) -> 0 | M11: =COUNTA(C11:G11) -> 5

Sheet Day 2
D2: Cell Reference
C4: 1 | D4: relative
C5: 2 | D5: absolute
C6: 3 | D6: circular
C7: 4 | D7: 3d cell
C8: 5 | D8: mixed cell
H9: GST | I9: 0.18
G10: Relative Reference | H10: Absolute Reference
D11: Sno | E11: Sales | F11: Profit | G11: CP | H11: Tax Collect
D12: 1 | E12: 104 | F12: 65 | G12: =E12-F12 -> 39 | H12: =E12*$I$9 -> 18.72
D13: 2 | E13: 151 | F13: 124 | G13: =E13-F13 -> 27 | H13: =E13*$I$9 -> 27.18
D14: 3 | E14: 197 | F14: 151 | G14: =E14-F14 -> 46 | H14: =E14*$I$9 -> 35.46
D15: 4 | E15: 109 | F15: 66 | G15: =E15-F15 -> 43 | H15: =E15*$I$9 -> 19.62
D16: 5 | E16: 147 | F16: 129 | G16: =E16-F16 -> 18 | H16: =E16*$I$9 -> 26.46
D20: Circular Reference
D21: Total Sales | E21: 450000
D22: Month Expense | E22: 20000
D23: Rent | E23: =E24*12% -> 46071.429
D24: Profit | E24: =E21-E22-E23 -> 383928.57
B29: Mixed Reference
D30: Tax Rate
D31: 0.18 | E31: 0.2 | F31: 0.25 | G31: 0.3
B32: Target Sales | C32: 1500 | D32: =$C32*D$31 -> 270 | E32: =$C32*E$31 -> 300 | F32: =$C32*F$31 -> 375 | G32: =$C32*G$31 -> 450
C33: 1700 | D33: =$C33*D$31 -> 306 | E33: =$C33*E$31 -> 340 | F33: =$C33*F$31 -> 425 | G33: =$C33*G$31 -> 510
C34: 1900 | D34: =$C34*D$31 -> 342 | E34: =$C34*E$31 -> 380 | F34: =$C34*F$31 -> 475 | G34: =$C34*G$31 -> 570
C35: 2100 | D35: =$C35*D$31 -> 378 | E35: =$C35*E$31 -> 420 | F35: =$C35*F$31 -> 525 | G35: =$C35*G$31 -> 630

Sheet Sheet2
A1: Sales
A2: 104
A3: 151
A4: 197
A5: 109
A6: 147

Sheet Sheet3
A1: Profit
A2: 65
A3: 124
A4: 151
A5: 66
A6: 129

Sheet 3d reference
A1: Cost Profit
A2: =Sheet2!A2-Sheet3!A2 -> 39
A3: =Sheet2!A3-Sheet3!A3 -> 27
A4: =Sheet2!A4-Sheet3!A4 -> 46
A5: =Sheet2!A5-Sheet3!A5 -> 43
A6: =Sheet2!A6-Sheet3!A6 -> 18

Sheet Day 3
A1: Text Formatting
B4: Sno | C4: Invoice ID | D4: Sales
B5: 1 | C5: 12542
B6: 2 | C6: 32565
B7: 3 | C7: 25569
B8: 4 | C8: 15421
B9: 5 | C9: 10020
B10: 6 | C10: 0
B11: 7 | C11: 221 | G11: DATE SHORT CUT
B12: 8 | C12: 2116 | G12: CTRL + ;
B13: 9 | C13: 51536 | G13: 45813
B14: 10 | C14: 222563 | G14: TIME SHORTCUT
G15: 0.56041667
G16: CTRL+SHIFT+;
C17: "OLA-NOIDA-2025-"00000
C19: CTRL+1
C20: NUMBER->CUSTOM

Sheet Sheet8
A1: Month | B1: Sales | C1: Profit | D1: Sales | E1: Profit
A2: JAN | B2: 45 | C2: 10 | D2: 45 | E2: 10
A3: FEB | B3: 50 | C3: 12 | D3: 46.628571 | E3: 11.142857
A4: MAR | B4: 53 | C4: 11 | D4: 48.257143 | E4: 12.285714
A5: APR | B5: 50 | C5: 15 | D5: 49.885714 | E5: 13.428571
A6: MAY | B6: 55 | C6: 14 | D6: 51.514286 | E6: 14.571429
A7: JUN | B7: 54 | C7: 16 | D7: 53.142857 | E7: 15.714286
A8: JUL | B8: 56.866667 | C8: 17 | D8: 54.771429 | E8: 16.857143
A9: AUG | B9: 58.495238 | C9: 18.142857 | D9: 56.4 | E9: 18
A10: SEP | B10: 60.12381 | C10: 19.285714 | D10: 58.028571 | E10: 19.142857
A11: OCT | B11: 61.752381 | C11: 20.428571 | D11: 59.657143 | E11: 20.285714
A12: NOV | B12: 63.380952 | C12: 21.571429 | D12: 61.285714 | E12: 21.428571
A13: DEC | B13: 65.009524 | C13: 22.714286 | D13: 62.914286 | E13: 22.571429

Sheet Sheet7
A1: 45817 | B1: 6 | C1: 2025 | D1: 9
A2: 45818 | B2: 6 | C2: 2025 | D2: 10
A3: 45819 | B3: 6 | C3: 2025 | D3: 11
A4: 45820 | B4: 6 | C4: 2025 | D4: 12
A5: 45821 | B5: 6 | C5: 2025 | D5: 13
A6: 45822 | B6: 6 | C6: 2025 | D6: 14
A7: 45823 | B7: 6 | C7: 2025 | D7: 15
A8: 45824 | B8: 6 | C8: 2025 | D8: 16
A9: 45825 | B9: 6 | C9: 2025 | D9: 17
A10: 45826 | B10: 6 | C10: 2025 | D10: 18
A11: 45827 | B11: 6 | C11: 2025 | D11: 19
A12: 45828 | B12: 6 | C12: 2025 | D12: 20
... A22: 45838 | B22: 6 | C22: 2025 | D22: 30

Sheet Sheet4
A1: First Name | B1: Last Name | C1: Final Column
A2: Aman | B2: Kumar | C2: Mr Aman Kumar Grastech
A3: Karan | B3: Mishra | C3: Mr Karan Mishra Grastech
A4: Ravi | B4: Verma | C4: Mr Ravi Verma Grastech
A5: Mohan | B5: Narang | C5: Mr Mohan Narang Grastech

Sheet Sheet6
A1: S no | B1: Order date | C1: Day | D1: Days Name | E1: Year | F1: Month Name | G1: Sales | H1: Profit | I1: Qty | J1: Profit | K1: Qty
A2: 1 | B2: 45292 | C2: =B2 -> 45292 | D2: =C2 -> 45292 | E2: =D2 -> 45292 | F2: =E2 -> 45292 | G2: 427 | H2: =RANDBETWEEN(-100,1000) -> 628 | I2: =RANDBETWEEN(1,10) -> 7 | J2: =RANDBETWEEN(-100,1000) -> 230 | K2: =RANDBETWEEN(1,10) -> 4
A3: 2 | B3: 45293 | C3: =B3 -> 45293 | D3: =C3 -> 45293 | E3: =D3 -> 45293 | F3: =E3 -> 45293 | G3: 109 | H3: =RANDBETWEEN(-100,1000) -> 654 | I3: =RANDBETWEEN(1,10) -> 10 | J3: =RANDBETWEEN(-100,1000) -> 992 | K3: =RANDBETWEEN(1,10) -> 10
A4: 3 | B4: 45294 | C4: =B4 -> 45294 | D4: =C4 -> 45294 | E4: =D4 -> 45294 | F4: =E4 -> 45294 | G4: 111 | H4: =RANDBETWEEN(-100,1000) -> 976 | I4: =RANDBETWEEN(1,10) -> 1 | J4: =RANDBETWEEN(-100,1000) -> 927 | K4: =RANDBETWEEN(1,10) -> 10
A5: 4 | B5: 45295 | C5: =B5 -> 45295 | D5: =C5 -> 45295 | E5: =D5 -> 45295 | F5: =E5 -> 45295 | G5: 257 | H5: =RANDBETWEEN(-100,1000) -> 854 | I5: =RANDBETWEEN(1,10) -> 5 | J5: =RANDBETWEEN(-100,1000) -> 30 | K5: =RANDBETWEEN(1,10) -> 9
A6: 5 | B6: 45296 | C6: =B6 -> 45296 | D6: =C6 -> 45296 | E6: =D6 -> 45296 | F6: =E6 -> 45296 | G6: 251 | H6: =RANDBETWEEN(-100,1000) -> 571 | I6: =RANDBETWEEN(1,10) -> 10 | J6: =RANDBETWEEN(-100,1000) -> 770 | K6: =RANDBETWEEN(1,10) -> 8
A7: 6 | B7: 45297 | C7: =B7 -> 45297 | D7: =C7 -> 45297 | E7: =D7 -> 45297 | F7: =E7 -> 45297 | G7: 122 | H7: =RANDBETWEEN(-100,1000) -> 731 | I7: =RANDBETWEEN(1,10) -> 9 | J7: =RANDBETWEEN(-100,1000) -> 794 | K7: =RANDBETWEEN(1,10) -> 2
A8: 7 | B8: 45298 | C8: =B8 -> 45298 | D8: =C8 -> 45298 | E8: =D8 -> 45298 | F8: =E8 -> 45298 | G8: 403 | H8: =RANDBETWEEN(-100,1000) -> 808 | I8: =RANDBETWEEN(1,10) -> 1 | J8: =RANDBETWEEN(-100,1000) -> 344 | K8: =RANDBETWEEN(1,10) -> 10
A9: 8 | B9: 45299 | C9: =B9 -> 45299 | D9: =C9 -> 45299 | E9: =D9 -> 45299 | F9: =E9 -> 45299 | G9: 100 | H9: =RANDBETWEEN(-100,1000) -> 379 | I9: =RANDBETWEEN(1,10) -> 7 | J9: =RANDBETWEEN(-100,1000) -> 63 | K9: =RANDBETWEEN(1,10) -> 4
A10: 9 | B10: 45300 | C10: =B10 -> 45300 | D10: =C10 -> 45300 | E10: =D10 -> 45300 | F10: =E10 -> 45300 | G10: 397 | H10: =RANDBETWEEN(-100,1000) -> 598 | I10: =RANDBETWEEN(1,10) -> 8 | J10: =RANDBETWEEN(-100,1000) -> 690 | K10: =RANDBETWEEN(1,10) -> 7
A11: 10 | B11: 45301 | C11: =B11 -> 45301 | D11: =C11 -> 45301 | E11: =D11 -> 45301 | F11: =E11 -> 45301 | G11: 160 | H11: =RANDBETWEEN(-100,1000) -> 770 | I11: =RANDBETWEEN(1,10) -> 4 | J11: =RANDBETWEEN(-100,1000) -> 866 | K11: =RANDBETWEEN(1,10) -> 8
A12: 11 | B12: 45302 | C12: =B12 -> 45302 | D12: =C12 -> 45302 | E12: =D12 -> 45302 | F12: =E12 -> 45302 | G12: 126 | H12: =RANDBETWEEN(-100,1000) -> 300 | I12: =RANDBETWEEN(1,10) -> 7 | J12: =RANDBETWEEN(-100,1000) -> 5 | K12: =RANDBETWEEN(1,10) -> 4
A13: 12 | B13: 45303 | C13: =B13 -> 45303 | D13: =C13 -> 45303 | E13: =D13 -> 45303 | F13: =E13 -> 45303 | G13: 335 | H13: =RANDBETWEEN(-100,1000) -> 65 | I13: =RANDBETWEEN(1,10) -> 5 | J13: =RANDBETWEEN(-100,1000) -> 237 | K13: =RANDBETWEEN(1,10) -> 1
... A732: 731 | B732: 46022 | C732: =B732 -> 46022 | D732: =C732 -> 46022 | E732: =D732 -> 46022 | F732: =E732 -> 46022 | G732: 449 | H732: =RANDBETWEEN(-100,1000) -> 316 | I732: =RANDBETWEEN(1,10) -> 8 | J732: =RANDBETWEEN(-100,1000) -> 430 | K732: =RANDBETWEEN(1,10) -> 3

Sheet DAY 4
